radio_t/__init__.py
radio_t-1.0.dist-info/METADATA
radio_t-1.0.dist-info/WHEEL
radio_t-1.0.dist-info/top_level.txt
radio_t-1.0.dist-info/RECORD
